{"name":"root","content":{"../node_modules/invariant/browser.js":{"id":"../node_modules/invariant/browser.js","buildMeta":{"providedExports":true}},"../node_modules/react-dom/index.js":{"id":"../node_modules/react-dom/index.js","buildMeta":{"providedExports":true}},"../node_modules/react-router/es/index.js":{"id":"../node_modules/react-router/es/index.js","buildMeta":{"exportsType":"namespace","providedExports":["MemoryRouter","Prompt","Redirect","Route","Router","StaticRouter","Switch","matchPath","withRouter"]}},"../node_modules/react-router-dom/es/index.js":{"id":"../node_modules/react-router-dom/es/index.js","buildMeta":{"exportsType":"namespace","providedExports":["BrowserRouter","HashRouter","Link","MemoryRouter","NavLink","Prompt","Redirect","Route","Router","StaticRouter","Switch","matchPath","withRouter"]}},"../node_modules/redux/es/redux.js":{"id":"../node_modules/redux/es/redux.js","buildMeta":{"exportsType":"namespace","providedExports":["createStore","combineReducers","bindActionCreators","applyMiddleware","compose","__DO_NOT_USE__ActionTypes"]}},"../node_modules/react-redux/es/index.js":{"id":"../node_modules/react-redux/es/index.js","buildMeta":{"exportsType":"namespace","providedExports":["Provider","createProvider","connectAdvanced","connect"]}},"../node_modules/redux-thunk/lib/index.js":{"id":"../node_modules/redux-thunk/lib/index.js","buildMeta":{"providedExports":true}},"../node_modules/redux-form/es/index.js":{"id":"../node_modules/redux-form/es/index.js","buildMeta":{"exportsType":"namespace","providedExports":["defaultShouldAsyncValidate","defaultShouldValidate","defaultShouldError","defaultShouldWarn","Form","FormSection","SubmissionError","propTypes","fieldInputPropTypes","fieldMetaPropTypes","fieldPropTypes","fieldArrayFieldsPropTypes","fieldArrayMetaPropTypes","fieldArrayPropTypes","formPropTypes","Field","Fields","FieldArray","formValueSelector","formValues","getFormError","getFormNames","getFormValues","getFormInitialValues","getFormSyncErrors","getFormMeta","getFormAsyncErrors","getFormSyncWarnings","getFormSubmitErrors","isDirty","isInvalid","isPristine","isValid","isSubmitting","hasSubmitSucceeded","hasSubmitFailed","reduxForm","reducer","values","actionTypes","arrayInsert","arrayMove","arrayPop","arrayPush","arrayRemove","arrayRemoveAll","arrayShift","arraySplice","arraySwap","arrayUnshift","autofill","blur","change","clearAsyncError","clearFields","clearSubmitErrors","destroy","focus","initialize","registerField","reset","resetSection","setSubmitFailed","setSubmitSucceeded","startAsyncValidation","startSubmit","stopAsyncValidation","stopSubmit","submit","touch","unregisterField","untouch","updateSyncWarnings"]}},"../node_modules/prop-types/index.js":{"id":"../node_modules/prop-types/index.js","buildMeta":{"providedExports":true}},"../node_modules/prop-types/factoryWithTypeCheckers.js":{"id":"../node_modules/prop-types/factoryWithTypeCheckers.js","buildMeta":{"providedExports":true}},"../node_modules/fbjs/lib/emptyFunction.js":{"id":"../node_modules/fbjs/lib/emptyFunction.js","buildMeta":{"providedExports":true}},"../node_modules/fbjs/lib/invariant.js":{"id":"../node_modules/fbjs/lib/invariant.js","buildMeta":{"providedExports":true}},"../node_modules/fbjs/lib/warning.js":{"id":"../node_modules/fbjs/lib/warning.js","buildMeta":{"providedExports":true}},"../node_modules/object-assign/index.js":{"id":"../node_modules/object-assign/index.js","buildMeta":{"providedExports":true}},"../node_modules/prop-types/lib/ReactPropTypesSecret.js":{"id":"../node_modules/prop-types/lib/ReactPropTypesSecret.js","buildMeta":{"providedExports":true}},"../node_modules/prop-types/checkPropTypes.js":{"id":"../node_modules/prop-types/checkPropTypes.js","buildMeta":{"providedExports":true}},"../node_modules/redux-form/es/actions.js":{"id":"../node_modules/redux-form/es/actions.js","buildMeta":{"exportsType":"namespace","providedExports":["default"]}},"../node_modules/redux-form/es/actionTypes.js":{"id":"../node_modules/redux-form/es/actionTypes.js","buildMeta":{"exportsType":"namespace","providedExports":["prefix","ARRAY_INSERT","ARRAY_MOVE","ARRAY_POP","ARRAY_PUSH","ARRAY_REMOVE","ARRAY_REMOVE_ALL","ARRAY_SHIFT","ARRAY_SPLICE","ARRAY_UNSHIFT","ARRAY_SWAP","AUTOFILL","BLUR","CHANGE","CLEAR_FIELDS","CLEAR_SUBMIT","CLEAR_SUBMIT_ERRORS","CLEAR_ASYNC_ERROR","DESTROY","FOCUS","INITIALIZE","REGISTER_FIELD","RESET","RESET_SECTION","SET_SUBMIT_FAILED","SET_SUBMIT_SUCCEEDED","START_ASYNC_VALIDATION","START_SUBMIT","STOP_ASYNC_VALIDATION","STOP_SUBMIT","SUBMIT","TOUCH","UNREGISTER_FIELD","UNTOUCH","UPDATE_SYNC_ERRORS","UPDATE_SYNC_WARNINGS"]}},"../node_modules/redux-form/es/defaultShouldAsyncValidate.js":{"id":"../node_modules/redux-form/es/defaultShouldAsyncValidate.js","buildMeta":{"exportsType":"namespace","providedExports":["default"]}},"../node_modules/redux-form/es/defaultShouldValidate.js":{"id":"../node_modules/redux-form/es/defaultShouldValidate.js","buildMeta":{"exportsType":"namespace","providedExports":["default"]}},"../node_modules/redux-form/es/defaultShouldError.js":{"id":"../node_modules/redux-form/es/defaultShouldError.js","buildMeta":{"exportsType":"namespace","providedExports":["default"]}},"../node_modules/redux-form/es/defaultShouldWarn.js":{"id":"../node_modules/redux-form/es/defaultShouldWarn.js","buildMeta":{"exportsType":"namespace","providedExports":["default"]}},"../node_modules/redux-form/es/Form.js":{"id":"../node_modules/redux-form/es/Form.js","buildMeta":{"exportsType":"namespace","providedExports":["default"]}},"../node_modules/redux-form/es/FormSection.js":{"id":"../node_modules/redux-form/es/FormSection.js","buildMeta":{"exportsType":"namespace","providedExports":["default"]}},"../node_modules/redux-form/es/SubmissionError.js":{"id":"../node_modules/redux-form/es/SubmissionError.js","buildMeta":{"exportsType":"namespace","providedExports":["default"]}},"../node_modules/redux-form/es/propTypes.js":{"id":"../node_modules/redux-form/es/propTypes.js","buildMeta":{"exportsType":"namespace","providedExports":["formPropTypes","fieldInputPropTypes","fieldMetaPropTypes","fieldArrayMetaPropTypes","fieldArrayFieldsPropTypes","fieldPropTypes","fieldArrayPropTypes","default"]}},"../node_modules/redux-form/es/Field.js":{"id":"../node_modules/redux-form/es/Field.js","buildMeta":{"exportsType":"namespace","providedExports":["default"]}},"../node_modules/redux-form/es/Fields.js":{"id":"../node_modules/redux-form/es/Fields.js","buildMeta":{"exportsType":"namespace","providedExports":["default"]}},"../node_modules/redux-form/es/FieldArray.js":{"id":"../node_modules/redux-form/es/FieldArray.js","buildMeta":{"exportsType":"namespace","providedExports":["default"]}},"../node_modules/redux-form/es/formValueSelector.js":{"id":"../node_modules/redux-form/es/formValueSelector.js","buildMeta":{"exportsType":"namespace","providedExports":["default"]}},"../node_modules/redux-form/es/formValues.js":{"id":"../node_modules/redux-form/es/formValues.js","buildMeta":{"exportsType":"namespace","providedExports":["default"]}},"../node_modules/redux-form/es/getFormError.js":{"id":"../node_modules/redux-form/es/getFormError.js","buildMeta":{"exportsType":"namespace","providedExports":["default"]}},"../node_modules/redux-form/es/getFormNames.js":{"id":"../node_modules/redux-form/es/getFormNames.js","buildMeta":{"exportsType":"namespace","providedExports":["default"]}},"../node_modules/redux-form/es/getFormValues.js":{"id":"../node_modules/redux-form/es/getFormValues.js","buildMeta":{"exportsType":"namespace","providedExports":["default"]}},"../node_modules/redux-form/es/getFormInitialValues.js":{"id":"../node_modules/redux-form/es/getFormInitialValues.js","buildMeta":{"exportsType":"namespace","providedExports":["default"]}},"../node_modules/redux-form/es/getFormSyncErrors.js":{"id":"../node_modules/redux-form/es/getFormSyncErrors.js","buildMeta":{"exportsType":"namespace","providedExports":["default"]}},"../node_modules/redux-form/es/getFormMeta.js":{"id":"../node_modules/redux-form/es/getFormMeta.js","buildMeta":{"exportsType":"namespace","providedExports":["default"]}},"../node_modules/redux-form/es/getFormAsyncErrors.js":{"id":"../node_modules/redux-form/es/getFormAsyncErrors.js","buildMeta":{"exportsType":"namespace","providedExports":["default"]}},"../node_modules/redux-form/es/getFormSyncWarnings.js":{"id":"../node_modules/redux-form/es/getFormSyncWarnings.js","buildMeta":{"exportsType":"namespace","providedExports":["default"]}},"../node_modules/redux-form/es/getFormSubmitErrors.js":{"id":"../node_modules/redux-form/es/getFormSubmitErrors.js","buildMeta":{"exportsType":"namespace","providedExports":["default"]}},"../node_modules/redux-form/es/isDirty.js":{"id":"../node_modules/redux-form/es/isDirty.js","buildMeta":{"exportsType":"namespace","providedExports":["default"]}},"../node_modules/redux-form/es/isInvalid.js":{"id":"../node_modules/redux-form/es/isInvalid.js","buildMeta":{"exportsType":"namespace","providedExports":["default"]}},"../node_modules/redux-form/es/isPristine.js":{"id":"../node_modules/redux-form/es/isPristine.js","buildMeta":{"exportsType":"namespace","providedExports":["default"]}},"../node_modules/redux-form/es/isValid.js":{"id":"../node_modules/redux-form/es/isValid.js","buildMeta":{"exportsType":"namespace","providedExports":["default"]}},"../node_modules/redux-form/es/isSubmitting.js":{"id":"../node_modules/redux-form/es/isSubmitting.js","buildMeta":{"exportsType":"namespace","providedExports":["default"]}},"../node_modules/redux-form/es/hasSubmitSucceeded.js":{"id":"../node_modules/redux-form/es/hasSubmitSucceeded.js","buildMeta":{"exportsType":"namespace","providedExports":["default"]}},"../node_modules/redux-form/es/hasSubmitFailed.js":{"id":"../node_modules/redux-form/es/hasSubmitFailed.js","buildMeta":{"exportsType":"namespace","providedExports":["default"]}},"../node_modules/redux-form/es/reduxForm.js":{"id":"../node_modules/redux-form/es/reduxForm.js","buildMeta":{"exportsType":"namespace","providedExports":["default"]}},"../node_modules/redux-form/es/reducer.js":{"id":"../node_modules/redux-form/es/reducer.js","buildMeta":{"exportsType":"namespace","providedExports":["default"]}},"../node_modules/redux-form/es/values.js":{"id":"../node_modules/redux-form/es/values.js","buildMeta":{"exportsType":"namespace","providedExports":["default"]}},"../node_modules/redux-form/es/createValues.js":{"id":"../node_modules/redux-form/es/createValues.js","buildMeta":{"exportsType":"namespace","providedExports":["default"]}},"../node_modules/redux-form/es/structure/plain/index.js":{"id":"../node_modules/redux-form/es/structure/plain/index.js","buildMeta":{"exportsType":"namespace","providedExports":["default"]}},"../node_modules/redux-form/es/structure/plain/splice.js":{"id":"../node_modules/redux-form/es/structure/plain/splice.js","buildMeta":{"exportsType":"namespace","providedExports":["default"]}},"../node_modules/redux-form/es/structure/plain/getIn.js":{"id":"../node_modules/redux-form/es/structure/plain/getIn.js","buildMeta":{"exportsType":"namespace","providedExports":["default"]}},"../node_modules/redux-form/es/structure/plain/setIn.js":{"id":"../node_modules/redux-form/es/structure/plain/setIn.js","buildMeta":{"exportsType":"namespace","providedExports":["default"]}},"../node_modules/redux-form/es/structure/plain/deepEqual.js":{"id":"../node_modules/redux-form/es/structure/plain/deepEqual.js","buildMeta":{"exportsType":"namespace","providedExports":["default"]}},"../node_modules/redux-form/es/structure/plain/deleteIn.js":{"id":"../node_modules/redux-form/es/structure/plain/deleteIn.js","buildMeta":{"exportsType":"namespace","providedExports":["default"]}},"../node_modules/redux-form/es/structure/plain/keys.js":{"id":"../node_modules/redux-form/es/structure/plain/keys.js","buildMeta":{"exportsType":"namespace","providedExports":["default"]}},"../node_modules/lodash-es/toPath.js":{"id":"../node_modules/lodash-es/toPath.js","buildMeta":{"exportsType":"namespace","providedExports":["default"]}},"../node_modules/lodash-es/_arrayMap.js":{"id":"../node_modules/lodash-es/_arrayMap.js","buildMeta":{"exportsType":"namespace","providedExports":["default"]}},"../node_modules/lodash-es/_copyArray.js":{"id":"../node_modules/lodash-es/_copyArray.js","buildMeta":{"exportsType":"namespace","providedExports":["default"]}},"../node_modules/lodash-es/isArray.js":{"id":"../node_modules/lodash-es/isArray.js","buildMeta":{"exportsType":"namespace","providedExports":["default"]}},"../node_modules/lodash-es/isSymbol.js":{"id":"../node_modules/lodash-es/isSymbol.js","buildMeta":{"exportsType":"namespace","providedExports":["default"]}},"../node_modules/lodash-es/_stringToPath.js":{"id":"../node_modules/lodash-es/_stringToPath.js","buildMeta":{"exportsType":"namespace","providedExports":["default"]}},"../node_modules/lodash-es/_toKey.js":{"id":"../node_modules/lodash-es/_toKey.js","buildMeta":{"exportsType":"namespace","providedExports":["default"]}},"../node_modules/lodash-es/toString.js":{"id":"../node_modules/lodash-es/toString.js","buildMeta":{"exportsType":"namespace","providedExports":["default"]}},"../node_modules/lodash-es/_baseToString.js":{"id":"../node_modules/lodash-es/_baseToString.js","buildMeta":{"exportsType":"namespace","providedExports":["default"]}},"../node_modules/lodash-es/_Symbol.js":{"id":"../node_modules/lodash-es/_Symbol.js","buildMeta":{"exportsType":"namespace","providedExports":["default"]}},"../node_modules/lodash-es/_root.js":{"id":"../node_modules/lodash-es/_root.js","buildMeta":{"exportsType":"namespace","providedExports":["default"]}},"../node_modules/lodash-es/_freeGlobal.js":{"id":"../node_modules/lodash-es/_freeGlobal.js","buildMeta":{"exportsType":"namespace","providedExports":["default"]}},"../node_modules/webpack/buildin/global.js":{"id":"../node_modules/webpack/buildin/global.js","buildMeta":{"providedExports":true}},"../node_modules/lodash-es/_memoizeCapped.js":{"id":"../node_modules/lodash-es/_memoizeCapped.js","buildMeta":{"exportsType":"namespace","providedExports":["default"]}},"../node_modules/lodash-es/memoize.js":{"id":"../node_modules/lodash-es/memoize.js","buildMeta":{"exportsType":"namespace","providedExports":["default"]}},"../node_modules/lodash-es/_MapCache.js":{"id":"../node_modules/lodash-es/_MapCache.js","buildMeta":{"exportsType":"namespace","providedExports":["default"]}},"../node_modules/lodash-es/_mapCacheClear.js":{"id":"../node_modules/lodash-es/_mapCacheClear.js","buildMeta":{"exportsType":"namespace","providedExports":["default"]}},"../node_modules/lodash-es/_mapCacheDelete.js":{"id":"../node_modules/lodash-es/_mapCacheDelete.js","buildMeta":{"exportsType":"namespace","providedExports":["default"]}},"../node_modules/lodash-es/_mapCacheGet.js":{"id":"../node_modules/lodash-es/_mapCacheGet.js","buildMeta":{"exportsType":"namespace","providedExports":["default"]}},"../node_modules/lodash-es/_mapCacheHas.js":{"id":"../node_modules/lodash-es/_mapCacheHas.js","buildMeta":{"exportsType":"namespace","providedExports":["default"]}},"../node_modules/lodash-es/_mapCacheSet.js":{"id":"../node_modules/lodash-es/_mapCacheSet.js","buildMeta":{"exportsType":"namespace","providedExports":["default"]}},"../node_modules/lodash-es/_getMapData.js":{"id":"../node_modules/lodash-es/_getMapData.js","buildMeta":{"exportsType":"namespace","providedExports":["default"]}},"../node_modules/lodash-es/_isKeyable.js":{"id":"../node_modules/lodash-es/_isKeyable.js","buildMeta":{"exportsType":"namespace","providedExports":["default"]}},"../node_modules/lodash-es/_Hash.js":{"id":"../node_modules/lodash-es/_Hash.js","buildMeta":{"exportsType":"namespace","providedExports":["default"]}},"../node_modules/lodash-es/_ListCache.js":{"id":"../node_modules/lodash-es/_ListCache.js","buildMeta":{"exportsType":"namespace","providedExports":["default"]}},"../node_modules/lodash-es/_Map.js":{"id":"../node_modules/lodash-es/_Map.js","buildMeta":{"exportsType":"namespace","providedExports":["default"]}},"../node_modules/lodash-es/_getNative.js":{"id":"../node_modules/lodash-es/_getNative.js","buildMeta":{"exportsType":"namespace","providedExports":["default"]}},"../node_modules/lodash-es/_baseIsNative.js":{"id":"../node_modules/lodash-es/_baseIsNative.js","buildMeta":{"exportsType":"namespace","providedExports":["default"]}},"../node_modules/lodash-es/_getValue.js":{"id":"../node_modules/lodash-es/_getValue.js","buildMeta":{"exportsType":"namespace","providedExports":["default"]}},"../node_modules/lodash-es/isFunction.js":{"id":"../node_modules/lodash-es/isFunction.js","buildMeta":{"exportsType":"namespace","providedExports":["default"]}},"../node_modules/lodash-es/_isMasked.js":{"id":"../node_modules/lodash-es/_isMasked.js","buildMeta":{"exportsType":"namespace","providedExports":["default"]}},"../node_modules/lodash-es/isObject.js":{"id":"../node_modules/lodash-es/isObject.js","buildMeta":{"exportsType":"namespace","providedExports":["default"]}},"../node_modules/lodash-es/_toSource.js":{"id":"../node_modules/lodash-es/_toSource.js","buildMeta":{"exportsType":"namespace","providedExports":["default"]}},"../node_modules/lodash-es/_coreJsData.js":{"id":"../node_modules/lodash-es/_coreJsData.js","buildMeta":{"exportsType":"namespace","providedExports":["default"]}},"../node_modules/lodash-es/_baseGetTag.js":{"id":"../node_modules/lodash-es/_baseGetTag.js","buildMeta":{"exportsType":"namespace","providedExports":["default"]}},"../node_modules/lodash-es/_getRawTag.js":{"id":"../node_modules/lodash-es/_getRawTag.js","buildMeta":{"exportsType":"namespace","providedExports":["default"]}},"../node_modules/lodash-es/_objectToString.js":{"id":"../node_modules/lodash-es/_objectToString.js","buildMeta":{"exportsType":"namespace","providedExports":["default"]}},"../node_modules/lodash-es/_listCacheClear.js":{"id":"../node_modules/lodash-es/_listCacheClear.js","buildMeta":{"exportsType":"namespace","providedExports":["default"]}},"../node_modules/lodash-es/_listCacheDelete.js":{"id":"../node_modules/lodash-es/_listCacheDelete.js","buildMeta":{"exportsType":"namespace","providedExports":["default"]}},"../node_modules/lodash-es/_listCacheGet.js":{"id":"../node_modules/lodash-es/_listCacheGet.js","buildMeta":{"exportsType":"namespace","providedExports":["default"]}},"../node_modules/lodash-es/_listCacheHas.js":{"id":"../node_modules/lodash-es/_listCacheHas.js","buildMeta":{"exportsType":"namespace","providedExports":["default"]}},"../node_modules/lodash-es/_listCacheSet.js":{"id":"../node_modules/lodash-es/_listCacheSet.js","buildMeta":{"exportsType":"namespace","providedExports":["default"]}},"../node_modules/lodash-es/_assocIndexOf.js":{"id":"../node_modules/lodash-es/_assocIndexOf.js","buildMeta":{"exportsType":"namespace","providedExports":["default"]}},"../node_modules/lodash-es/eq.js":{"id":"../node_modules/lodash-es/eq.js","buildMeta":{"exportsType":"namespace","providedExports":["default"]}},"../node_modules/lodash-es/_hashClear.js":{"id":"../node_modules/lodash-es/_hashClear.js","buildMeta":{"exportsType":"namespace","providedExports":["default"]}},"../node_modules/lodash-es/_hashDelete.js":{"id":"../node_modules/lodash-es/_hashDelete.js","buildMeta":{"exportsType":"namespace","providedExports":["default"]}},"../node_modules/lodash-es/_hashGet.js":{"id":"../node_modules/lodash-es/_hashGet.js","buildMeta":{"exportsType":"namespace","providedExports":["default"]}},"../node_modules/lodash-es/_hashHas.js":{"id":"../node_modules/lodash-es/_hashHas.js","buildMeta":{"exportsType":"namespace","providedExports":["default"]}},"../node_modules/lodash-es/_hashSet.js":{"id":"../node_modules/lodash-es/_hashSet.js","buildMeta":{"exportsType":"namespace","providedExports":["default"]}},"../node_modules/lodash-es/_nativeCreate.js":{"id":"../node_modules/lodash-es/_nativeCreate.js","buildMeta":{"exportsType":"namespace","providedExports":["default"]}},"../node_modules/lodash-es/isObjectLike.js":{"id":"../node_modules/lodash-es/isObjectLike.js","buildMeta":{"exportsType":"namespace","providedExports":["default"]}},"../node_modules/lodash-es/isEqualWith.js":{"id":"../node_modules/lodash-es/isEqualWith.js","buildMeta":{"exportsType":"namespace","providedExports":["default"]}},"../node_modules/lodash-es/_baseIsEqual.js":{"id":"../node_modules/lodash-es/_baseIsEqual.js","buildMeta":{"exportsType":"namespace","providedExports":["default"]}},"../node_modules/lodash-es/_baseIsEqualDeep.js":{"id":"../node_modules/lodash-es/_baseIsEqualDeep.js","buildMeta":{"exportsType":"namespace","providedExports":["default"]}},"../node_modules/lodash-es/_Stack.js":{"id":"../node_modules/lodash-es/_Stack.js","buildMeta":{"exportsType":"namespace","providedExports":["default"]}},"../node_modules/lodash-es/_equalArrays.js":{"id":"../node_modules/lodash-es/_equalArrays.js","buildMeta":{"exportsType":"namespace","providedExports":["default"]}},"../node_modules/lodash-es/_equalByTag.js":{"id":"../node_modules/lodash-es/_equalByTag.js","buildMeta":{"exportsType":"namespace","providedExports":["default"]}},"../node_modules/lodash-es/_equalObjects.js":{"id":"../node_modules/lodash-es/_equalObjects.js","buildMeta":{"exportsType":"namespace","providedExports":["default"]}},"../node_modules/lodash-es/_getTag.js":{"id":"../node_modules/lodash-es/_getTag.js","buildMeta":{"exportsType":"namespace","providedExports":["default"]}},"../node_modules/lodash-es/isBuffer.js":{"id":"../node_modules/lodash-es/isBuffer.js","buildMeta":{"exportsType":"namespace","providedExports":["default"]}},"../node_modules/lodash-es/isTypedArray.js":{"id":"../node_modules/lodash-es/isTypedArray.js","buildMeta":{"exportsType":"namespace","providedExports":["default"]}},"../node_modules/lodash-es/_baseIsTypedArray.js":{"id":"../node_modules/lodash-es/_baseIsTypedArray.js","buildMeta":{"exportsType":"namespace","providedExports":["default"]}},"../node_modules/lodash-es/_baseUnary.js":{"id":"../node_modules/lodash-es/_baseUnary.js","buildMeta":{"exportsType":"namespace","providedExports":["default"]}},"../node_modules/lodash-es/_nodeUtil.js":{"id":"../node_modules/lodash-es/_nodeUtil.js","buildMeta":{"exportsType":"namespace","providedExports":["default"]}},"../node_modules/webpack/buildin/harmony-module.js":{"id":"../node_modules/webpack/buildin/harmony-module.js","buildMeta":{"providedExports":true}},"../node_modules/lodash-es/isLength.js":{"id":"../node_modules/lodash-es/isLength.js","buildMeta":{"exportsType":"namespace","providedExports":["default"]}},"../node_modules/lodash-es/stubFalse.js":{"id":"../node_modules/lodash-es/stubFalse.js","buildMeta":{"exportsType":"namespace","providedExports":["default"]}},"../node_modules/lodash-es/_DataView.js":{"id":"../node_modules/lodash-es/_DataView.js","buildMeta":{"exportsType":"namespace","providedExports":["default"]}},"../node_modules/lodash-es/_Promise.js":{"id":"../node_modules/lodash-es/_Promise.js","buildMeta":{"exportsType":"namespace","providedExports":["default"]}},"../node_modules/lodash-es/_Set.js":{"id":"../node_modules/lodash-es/_Set.js","buildMeta":{"exportsType":"namespace","providedExports":["default"]}},"../node_modules/lodash-es/_WeakMap.js":{"id":"../node_modules/lodash-es/_WeakMap.js","buildMeta":{"exportsType":"namespace","providedExports":["default"]}},"../node_modules/lodash-es/_getAllKeys.js":{"id":"../node_modules/lodash-es/_getAllKeys.js","buildMeta":{"exportsType":"namespace","providedExports":["default"]}},"../node_modules/lodash-es/_baseGetAllKeys.js":{"id":"../node_modules/lodash-es/_baseGetAllKeys.js","buildMeta":{"exportsType":"namespace","providedExports":["default"]}},"../node_modules/lodash-es/_getSymbols.js":{"id":"../node_modules/lodash-es/_getSymbols.js","buildMeta":{"exportsType":"namespace","providedExports":["default"]}},"../node_modules/lodash-es/keys.js":{"id":"../node_modules/lodash-es/keys.js","buildMeta":{"exportsType":"namespace","providedExports":["default"]}},"../node_modules/lodash-es/_arrayLikeKeys.js":{"id":"../node_modules/lodash-es/_arrayLikeKeys.js","buildMeta":{"exportsType":"namespace","providedExports":["default"]}},"../node_modules/lodash-es/_baseKeys.js":{"id":"../node_modules/lodash-es/_baseKeys.js","buildMeta":{"exportsType":"namespace","providedExports":["default"]}},"../node_modules/lodash-es/isArrayLike.js":{"id":"../node_modules/lodash-es/isArrayLike.js","buildMeta":{"exportsType":"namespace","providedExports":["default"]}},"../node_modules/lodash-es/_isPrototype.js":{"id":"../node_modules/lodash-es/_isPrototype.js","buildMeta":{"exportsType":"namespace","providedExports":["default"]}},"../node_modules/lodash-es/_nativeKeys.js":{"id":"../node_modules/lodash-es/_nativeKeys.js","buildMeta":{"exportsType":"namespace","providedExports":["default"]}},"../node_modules/lodash-es/_overArg.js":{"id":"../node_modules/lodash-es/_overArg.js","buildMeta":{"exportsType":"namespace","providedExports":["default"]}},"../node_modules/lodash-es/_baseTimes.js":{"id":"../node_modules/lodash-es/_baseTimes.js","buildMeta":{"exportsType":"namespace","providedExports":["default"]}},"../node_modules/lodash-es/isArguments.js":{"id":"../node_modules/lodash-es/isArguments.js","buildMeta":{"exportsType":"namespace","providedExports":["default"]}},"../node_modules/lodash-es/_isIndex.js":{"id":"../node_modules/lodash-es/_isIndex.js","buildMeta":{"exportsType":"namespace","providedExports":["default"]}},"../node_modules/lodash-es/_baseIsArguments.js":{"id":"../node_modules/lodash-es/_baseIsArguments.js","buildMeta":{"exportsType":"namespace","providedExports":["default"]}},"../node_modules/lodash-es/_arrayFilter.js":{"id":"../node_modules/lodash-es/_arrayFilter.js","buildMeta":{"exportsType":"namespace","providedExports":["default"]}},"../node_modules/lodash-es/stubArray.js":{"id":"../node_modules/lodash-es/stubArray.js","buildMeta":{"exportsType":"namespace","providedExports":["default"]}},"../node_modules/lodash-es/_arrayPush.js":{"id":"../node_modules/lodash-es/_arrayPush.js","buildMeta":{"exportsType":"namespace","providedExports":["default"]}},"../node_modules/lodash-es/_Uint8Array.js":{"id":"../node_modules/lodash-es/_Uint8Array.js","buildMeta":{"exportsType":"namespace","providedExports":["default"]}},"../node_modules/lodash-es/_mapToArray.js":{"id":"../node_modules/lodash-es/_mapToArray.js","buildMeta":{"exportsType":"namespace","providedExports":["default"]}},"../node_modules/lodash-es/_setToArray.js":{"id":"../node_modules/lodash-es/_setToArray.js","buildMeta":{"exportsType":"namespace","providedExports":["default"]}},"../node_modules/lodash-es/_SetCache.js":{"id":"../node_modules/lodash-es/_SetCache.js","buildMeta":{"exportsType":"namespace","providedExports":["default"]}},"../node_modules/lodash-es/_arraySome.js":{"id":"../node_modules/lodash-es/_arraySome.js","buildMeta":{"exportsType":"namespace","providedExports":["default"]}},"../node_modules/lodash-es/_cacheHas.js":{"id":"../node_modules/lodash-es/_cacheHas.js","buildMeta":{"exportsType":"namespace","providedExports":["default"]}},"../node_modules/lodash-es/_setCacheAdd.js":{"id":"../node_modules/lodash-es/_setCacheAdd.js","buildMeta":{"exportsType":"namespace","providedExports":["default"]}},"../node_modules/lodash-es/_setCacheHas.js":{"id":"../node_modules/lodash-es/_setCacheHas.js","buildMeta":{"exportsType":"namespace","providedExports":["default"]}},"../node_modules/lodash-es/_stackClear.js":{"id":"../node_modules/lodash-es/_stackClear.js","buildMeta":{"exportsType":"namespace","providedExports":["default"]}},"../node_modules/lodash-es/_stackDelete.js":{"id":"../node_modules/lodash-es/_stackDelete.js","buildMeta":{"exportsType":"namespace","providedExports":["default"]}},"../node_modules/lodash-es/_stackGet.js":{"id":"../node_modules/lodash-es/_stackGet.js","buildMeta":{"exportsType":"namespace","providedExports":["default"]}},"../node_modules/lodash-es/_stackHas.js":{"id":"../node_modules/lodash-es/_stackHas.js","buildMeta":{"exportsType":"namespace","providedExports":["default"]}},"../node_modules/lodash-es/_stackSet.js":{"id":"../node_modules/lodash-es/_stackSet.js","buildMeta":{"exportsType":"namespace","providedExports":["default"]}},"../node_modules/redux-form/es/createReducer.js":{"id":"../node_modules/redux-form/es/createReducer.js","buildMeta":{"exportsType":"namespace","providedExports":["default"]}},"../node_modules/redux-form/es/deleteInWithCleanUp.js":{"id":"../node_modules/redux-form/es/deleteInWithCleanUp.js","buildMeta":{"exportsType":"namespace","providedExports":["default"]}},"../node_modules/redux-form/es/createReduxForm.js":{"id":"../node_modules/redux-form/es/createReduxForm.js","buildMeta":{"exportsType":"namespace","providedExports":["default"]}},"../node_modules/lodash-es/merge.js":{"id":"../node_modules/lodash-es/merge.js","buildMeta":{"exportsType":"namespace","providedExports":["default"]}},"../node_modules/lodash-es/mapValues.js":{"id":"../node_modules/lodash-es/mapValues.js","buildMeta":{"exportsType":"namespace","providedExports":["default"]}},"../node_modules/hoist-non-react-statics/index.js":{"id":"../node_modules/hoist-non-react-statics/index.js","buildMeta":{"providedExports":true}},"../node_modules/react/index.js":{"id":"../node_modules/react/index.js","buildMeta":{"providedExports":true}},"../node_modules/is-promise/index.js":{"id":"../node_modules/is-promise/index.js","buildMeta":{"providedExports":true}},"../node_modules/redux-form/es/asyncValidation.js":{"id":"../node_modules/redux-form/es/asyncValidation.js","buildMeta":{"exportsType":"namespace","providedExports":["default"]}},"../node_modules/redux-form/es/events/silenceEvent.js":{"id":"../node_modules/redux-form/es/events/silenceEvent.js","buildMeta":{"exportsType":"namespace","providedExports":["default"]}},"../node_modules/redux-form/es/events/silenceEvents.js":{"id":"../node_modules/redux-form/es/events/silenceEvents.js","buildMeta":{"exportsType":"namespace","providedExports":["default"]}},"../node_modules/redux-form/es/generateValidator.js":{"id":"../node_modules/redux-form/es/generateValidator.js","buildMeta":{"exportsType":"namespace","providedExports":["default"]}},"../node_modules/redux-form/es/handleSubmit.js":{"id":"../node_modules/redux-form/es/handleSubmit.js","buildMeta":{"exportsType":"namespace","providedExports":["default"]}},"../node_modules/redux-form/es/selectors/isValid.js":{"id":"../node_modules/redux-form/es/selectors/isValid.js","buildMeta":{"exportsType":"namespace","providedExports":["default"]}},"../node_modules/redux-form/es/util/getDisplayName.js":{"id":"../node_modules/redux-form/es/util/getDisplayName.js","buildMeta":{"exportsType":"namespace","providedExports":["default"]}},"../node_modules/redux-form/es/util/isHotReloading.js":{"id":"../node_modules/redux-form/es/util/isHotReloading.js","buildMeta":{"exportsType":"namespace","providedExports":["default"]}},"../node_modules/redux-form/es/hasError.js":{"id":"../node_modules/redux-form/es/hasError.js","buildMeta":{"exportsType":"namespace","providedExports":["default"]}},"../node_modules/redux-form/es/events/isEvent.js":{"id":"../node_modules/redux-form/es/events/isEvent.js","buildMeta":{"exportsType":"namespace","providedExports":["default"]}},"../node_modules/lodash-es/_baseAssignValue.js":{"id":"../node_modules/lodash-es/_baseAssignValue.js","buildMeta":{"exportsType":"namespace","providedExports":["default"]}},"../node_modules/lodash-es/_baseForOwn.js":{"id":"../node_modules/lodash-es/_baseForOwn.js","buildMeta":{"exportsType":"namespace","providedExports":["default"]}},"../node_modules/lodash-es/_baseIteratee.js":{"id":"../node_modules/lodash-es/_baseIteratee.js","buildMeta":{"exportsType":"namespace","providedExports":["default"]}},"../node_modules/lodash-es/_baseMatches.js":{"id":"../node_modules/lodash-es/_baseMatches.js","buildMeta":{"exportsType":"namespace","providedExports":["default"]}},"../node_modules/lodash-es/_baseMatchesProperty.js":{"id":"../node_modules/lodash-es/_baseMatchesProperty.js","buildMeta":{"exportsType":"namespace","providedExports":["default"]}},"../node_modules/lodash-es/identity.js":{"id":"../node_modules/lodash-es/identity.js","buildMeta":{"exportsType":"namespace","providedExports":["default"]}},"../node_modules/lodash-es/property.js":{"id":"../node_modules/lodash-es/property.js","buildMeta":{"exportsType":"namespace","providedExports":["default"]}},"../node_modules/lodash-es/_baseProperty.js":{"id":"../node_modules/lodash-es/_baseProperty.js","buildMeta":{"exportsType":"namespace","providedExports":["default"]}},"../node_modules/lodash-es/_basePropertyDeep.js":{"id":"../node_modules/lodash-es/_basePropertyDeep.js","buildMeta":{"exportsType":"namespace","providedExports":["default"]}},"../node_modules/lodash-es/_isKey.js":{"id":"../node_modules/lodash-es/_isKey.js","buildMeta":{"exportsType":"namespace","providedExports":["default"]}},"../node_modules/lodash-es/_baseGet.js":{"id":"../node_modules/lodash-es/_baseGet.js","buildMeta":{"exportsType":"namespace","providedExports":["default"]}},"../node_modules/lodash-es/_castPath.js":{"id":"../node_modules/lodash-es/_castPath.js","buildMeta":{"exportsType":"namespace","providedExports":["default"]}},"../node_modules/lodash-es/get.js":{"id":"../node_modules/lodash-es/get.js","buildMeta":{"exportsType":"namespace","providedExports":["default"]}},"../node_modules/lodash-es/hasIn.js":{"id":"../node_modules/lodash-es/hasIn.js","buildMeta":{"exportsType":"namespace","providedExports":["default"]}},"../node_modules/lodash-es/_isStrictComparable.js":{"id":"../node_modules/lodash-es/_isStrictComparable.js","buildMeta":{"exportsType":"namespace","providedExports":["default"]}},"../node_modules/lodash-es/_matchesStrictComparable.js":{"id":"../node_modules/lodash-es/_matchesStrictComparable.js","buildMeta":{"exportsType":"namespace","providedExports":["default"]}},"../node_modules/lodash-es/_baseHasIn.js":{"id":"../node_modules/lodash-es/_baseHasIn.js","buildMeta":{"exportsType":"namespace","providedExports":["default"]}},"../node_modules/lodash-es/_hasPath.js":{"id":"../node_modules/lodash-es/_hasPath.js","buildMeta":{"exportsType":"namespace","providedExports":["default"]}},"../node_modules/lodash-es/_baseIsMatch.js":{"id":"../node_modules/lodash-es/_baseIsMatch.js","buildMeta":{"exportsType":"namespace","providedExports":["default"]}},"../node_modules/lodash-es/_getMatchData.js":{"id":"../node_modules/lodash-es/_getMatchData.js","buildMeta":{"exportsType":"namespace","providedExports":["default"]}},"../node_modules/lodash-es/_baseFor.js":{"id":"../node_modules/lodash-es/_baseFor.js","buildMeta":{"exportsType":"namespace","providedExports":["default"]}},"../node_modules/lodash-es/_createBaseFor.js":{"id":"../node_modules/lodash-es/_createBaseFor.js","buildMeta":{"exportsType":"namespace","providedExports":["default"]}},"../node_modules/lodash-es/_defineProperty.js":{"id":"../node_modules/lodash-es/_defineProperty.js","buildMeta":{"exportsType":"namespace","providedExports":["default"]}},"../node_modules/lodash-es/_baseMerge.js":{"id":"../node_modules/lodash-es/_baseMerge.js","buildMeta":{"exportsType":"namespace","providedExports":["default"]}},"../node_modules/lodash-es/_createAssigner.js":{"id":"../node_modules/lodash-es/_createAssigner.js","buildMeta":{"exportsType":"namespace","providedExports":["default"]}},"../node_modules/lodash-es/_baseRest.js":{"id":"../node_modules/lodash-es/_baseRest.js","buildMeta":{"exportsType":"namespace","providedExports":["default"]}},"../node_modules/lodash-es/_isIterateeCall.js":{"id":"../node_modules/lodash-es/_isIterateeCall.js","buildMeta":{"exportsType":"namespace","providedExports":["default"]}},"../node_modules/lodash-es/_overRest.js":{"id":"../node_modules/lodash-es/_overRest.js","buildMeta":{"exportsType":"namespace","providedExports":["default"]}},"../node_modules/lodash-es/_setToString.js":{"id":"../node_modules/lodash-es/_setToString.js","buildMeta":{"exportsType":"namespace","providedExports":["default"]}},"../node_modules/lodash-es/_baseSetToString.js":{"id":"../node_modules/lodash-es/_baseSetToString.js","buildMeta":{"exportsType":"namespace","providedExports":["default"]}},"../node_modules/lodash-es/_shortOut.js":{"id":"../node_modules/lodash-es/_shortOut.js","buildMeta":{"exportsType":"namespace","providedExports":["default"]}},"../node_modules/lodash-es/constant.js":{"id":"../node_modules/lodash-es/constant.js","buildMeta":{"exportsType":"namespace","providedExports":["default"]}},"../node_modules/lodash-es/_apply.js":{"id":"../node_modules/lodash-es/_apply.js","buildMeta":{"exportsType":"namespace","providedExports":["default"]}},"../node_modules/lodash-es/_assignMergeValue.js":{"id":"../node_modules/lodash-es/_assignMergeValue.js","buildMeta":{"exportsType":"namespace","providedExports":["default"]}},"../node_modules/lodash-es/_baseMergeDeep.js":{"id":"../node_modules/lodash-es/_baseMergeDeep.js","buildMeta":{"exportsType":"namespace","providedExports":["default"]}},"../node_modules/lodash-es/keysIn.js":{"id":"../node_modules/lodash-es/keysIn.js","buildMeta":{"exportsType":"namespace","providedExports":["default"]}},"../node_modules/lodash-es/_safeGet.js":{"id":"../node_modules/lodash-es/_safeGet.js","buildMeta":{"exportsType":"namespace","providedExports":["default"]}},"../node_modules/lodash-es/_baseKeysIn.js":{"id":"../node_modules/lodash-es/_baseKeysIn.js","buildMeta":{"exportsType":"namespace","providedExports":["default"]}},"../node_modules/lodash-es/_nativeKeysIn.js":{"id":"../node_modules/lodash-es/_nativeKeysIn.js","buildMeta":{"exportsType":"namespace","providedExports":["default"]}},"../node_modules/lodash-es/_cloneBuffer.js":{"id":"../node_modules/lodash-es/_cloneBuffer.js","buildMeta":{"exportsType":"namespace","providedExports":["default"]}},"../node_modules/lodash-es/_cloneTypedArray.js":{"id":"../node_modules/lodash-es/_cloneTypedArray.js","buildMeta":{"exportsType":"namespace","providedExports":["default"]}},"../node_modules/lodash-es/_initCloneObject.js":{"id":"../node_modules/lodash-es/_initCloneObject.js","buildMeta":{"exportsType":"namespace","providedExports":["default"]}},"../node_modules/lodash-es/isArrayLikeObject.js":{"id":"../node_modules/lodash-es/isArrayLikeObject.js","buildMeta":{"exportsType":"namespace","providedExports":["default"]}},"../node_modules/lodash-es/isPlainObject.js":{"id":"../node_modules/lodash-es/isPlainObject.js","buildMeta":{"exportsType":"namespace","providedExports":["default"]}},"../node_modules/lodash-es/toPlainObject.js":{"id":"../node_modules/lodash-es/toPlainObject.js","buildMeta":{"exportsType":"namespace","providedExports":["default"]}},"../node_modules/lodash-es/_copyObject.js":{"id":"../node_modules/lodash-es/_copyObject.js","buildMeta":{"exportsType":"namespace","providedExports":["default"]}},"../node_modules/lodash-es/_assignValue.js":{"id":"../node_modules/lodash-es/_assignValue.js","buildMeta":{"exportsType":"namespace","providedExports":["default"]}},"../node_modules/lodash-es/_getPrototype.js":{"id":"../node_modules/lodash-es/_getPrototype.js","buildMeta":{"exportsType":"namespace","providedExports":["default"]}},"../node_modules/lodash-es/_baseCreate.js":{"id":"../node_modules/lodash-es/_baseCreate.js","buildMeta":{"exportsType":"namespace","providedExports":["default"]}},"../node_modules/lodash-es/_cloneArrayBuffer.js":{"id":"../node_modules/lodash-es/_cloneArrayBuffer.js","buildMeta":{"exportsType":"namespace","providedExports":["default"]}},"../node_modules/redux-form/es/selectors/hasSubmitFailed.js":{"id":"../node_modules/redux-form/es/selectors/hasSubmitFailed.js","buildMeta":{"exportsType":"namespace","providedExports":["default"]}},"../node_modules/redux-form/es/selectors/hasSubmitSucceeded.js":{"id":"../node_modules/redux-form/es/selectors/hasSubmitSucceeded.js","buildMeta":{"exportsType":"namespace","providedExports":["default"]}},"../node_modules/redux-form/es/selectors/isSubmitting.js":{"id":"../node_modules/redux-form/es/selectors/isSubmitting.js","buildMeta":{"exportsType":"namespace","providedExports":["default"]}},"../node_modules/redux-form/es/selectors/isPristine.js":{"id":"../node_modules/redux-form/es/selectors/isPristine.js","buildMeta":{"exportsType":"namespace","providedExports":["default"]}},"../node_modules/redux-form/es/selectors/isInvalid.js":{"id":"../node_modules/redux-form/es/selectors/isInvalid.js","buildMeta":{"exportsType":"namespace","providedExports":["default"]}},"../node_modules/redux-form/es/selectors/isDirty.js":{"id":"../node_modules/redux-form/es/selectors/isDirty.js","buildMeta":{"exportsType":"namespace","providedExports":["default"]}},"../node_modules/redux-form/es/selectors/getFormSubmitErrors.js":{"id":"../node_modules/redux-form/es/selectors/getFormSubmitErrors.js","buildMeta":{"exportsType":"namespace","providedExports":["default"]}},"../node_modules/redux-form/es/selectors/getFormSyncWarnings.js":{"id":"../node_modules/redux-form/es/selectors/getFormSyncWarnings.js","buildMeta":{"exportsType":"namespace","providedExports":["default"]}},"../node_modules/redux-form/es/selectors/getFormAsyncErrors.js":{"id":"../node_modules/redux-form/es/selectors/getFormAsyncErrors.js","buildMeta":{"exportsType":"namespace","providedExports":["default"]}},"../node_modules/redux-form/es/selectors/getFormMeta.js":{"id":"../node_modules/redux-form/es/selectors/getFormMeta.js","buildMeta":{"exportsType":"namespace","providedExports":["default"]}},"../node_modules/redux-form/es/selectors/getFormSyncErrors.js":{"id":"../node_modules/redux-form/es/selectors/getFormSyncErrors.js","buildMeta":{"exportsType":"namespace","providedExports":["default"]}},"../node_modules/redux-form/es/selectors/getFormInitialValues.js":{"id":"../node_modules/redux-form/es/selectors/getFormInitialValues.js","buildMeta":{"exportsType":"namespace","providedExports":["default"]}},"../node_modules/redux-form/es/selectors/getFormValues.js":{"id":"../node_modules/redux-form/es/selectors/getFormValues.js","buildMeta":{"exportsType":"namespace","providedExports":["default"]}},"../node_modules/redux-form/es/selectors/getFormNames.js":{"id":"../node_modules/redux-form/es/selectors/getFormNames.js","buildMeta":{"exportsType":"namespace","providedExports":["default"]}},"../node_modules/redux-form/es/selectors/getFormError.js":{"id":"../node_modules/redux-form/es/selectors/getFormError.js","buildMeta":{"exportsType":"namespace","providedExports":["default"]}},"../node_modules/redux-form/es/createFormValues.js":{"id":"../node_modules/redux-form/es/createFormValues.js","buildMeta":{"exportsType":"namespace","providedExports":["default"]}},"../node_modules/lodash-es/isEqual.js":{"id":"../node_modules/lodash-es/isEqual.js","buildMeta":{"exportsType":"namespace","providedExports":["default"]}},"../node_modules/lodash-es/isEmpty.js":{"id":"../node_modules/lodash-es/isEmpty.js","buildMeta":{"exportsType":"namespace","providedExports":["default"]}},"../node_modules/redux-form/es/util/prefixName.js":{"id":"../node_modules/redux-form/es/util/prefixName.js","buildMeta":{"exportsType":"namespace","providedExports":["default"]}},"../node_modules/redux-form/es/createFormValueSelector.js":{"id":"../node_modules/redux-form/es/createFormValueSelector.js","buildMeta":{"exportsType":"namespace","providedExports":["default"]}},"../node_modules/redux-form/es/createFieldArray.js":{"id":"../node_modules/redux-form/es/createFieldArray.js","buildMeta":{"exportsType":"namespace","providedExports":["default"]}},"../node_modules/redux-form/es/ConnectedFieldArray.js":{"id":"../node_modules/redux-form/es/ConnectedFieldArray.js","buildMeta":{"exportsType":"namespace","providedExports":["default"]}},"../node_modules/redux-form/es/createFieldArrayProps.js":{"id":"../node_modules/redux-form/es/createFieldArrayProps.js","buildMeta":{"exportsType":"namespace","providedExports":["default"]}},"../node_modules/redux-form/es/createFields.js":{"id":"../node_modules/redux-form/es/createFields.js","buildMeta":{"exportsType":"namespace","providedExports":["default"]}},"../node_modules/redux-form/es/ConnectedFields.js":{"id":"../node_modules/redux-form/es/ConnectedFields.js","buildMeta":{"exportsType":"namespace","providedExports":["default"]}},"../node_modules/redux-form/es/util/shallowCompare.js":{"id":"../node_modules/redux-form/es/util/shallowCompare.js","buildMeta":{"exportsType":"namespace","providedExports":["default"]}},"../node_modules/redux-form/es/createFieldProps.js":{"id":"../node_modules/redux-form/es/createFieldProps.js","buildMeta":{"exportsType":"namespace","providedExports":["default"]}},"../node_modules/redux-form/es/events/onChangeValue.js":{"id":"../node_modules/redux-form/es/events/onChangeValue.js","buildMeta":{"exportsType":"namespace","providedExports":["default"]}},"../node_modules/redux-form/es/events/getValue.js":{"id":"../node_modules/redux-form/es/events/getValue.js","buildMeta":{"exportsType":"namespace","providedExports":["default"]}},"../node_modules/redux-form/es/isReactNative.js":{"id":"../node_modules/redux-form/es/isReactNative.js","buildMeta":{"exportsType":"namespace","providedExports":["default"]}},"../node_modules/redux-form/es/createField.js":{"id":"../node_modules/redux-form/es/createField.js","buildMeta":{"exportsType":"namespace","providedExports":["default"]}},"../node_modules/redux-form/es/ConnectedField.js":{"id":"../node_modules/redux-form/es/ConnectedField.js","buildMeta":{"exportsType":"namespace","providedExports":["default"]}},"../node_modules/redux-form/es/util/eventConsts.js":{"id":"../node_modules/redux-form/es/util/eventConsts.js","buildMeta":{"exportsType":"namespace","providedExports":["dataKey"]}},"../node_modules/es6-error/es6/index.js":{"id":"../node_modules/es6-error/es6/index.js","buildMeta":{"exportsType":"namespace","providedExports":["default"]}},"../node_modules/react-redux/es/components/Provider.js":{"id":"../node_modules/react-redux/es/components/Provider.js","buildMeta":{"exportsType":"namespace","providedExports":["createProvider","default"]}},"../node_modules/react-redux/es/components/connectAdvanced.js":{"id":"../node_modules/react-redux/es/components/connectAdvanced.js","buildMeta":{"exportsType":"namespace","providedExports":["default"]}},"../node_modules/react-redux/es/connect/connect.js":{"id":"../node_modules/react-redux/es/connect/connect.js","buildMeta":{"exportsType":"namespace","providedExports":["createConnect","default"]}},"../node_modules/react-redux/es/utils/shallowEqual.js":{"id":"../node_modules/react-redux/es/utils/shallowEqual.js","buildMeta":{"exportsType":"namespace","providedExports":["default"]}},"../node_modules/react-redux/es/connect/mapDispatchToProps.js":{"id":"../node_modules/react-redux/es/connect/mapDispatchToProps.js","buildMeta":{"exportsType":"namespace","providedExports":["whenMapDispatchToPropsIsFunction","whenMapDispatchToPropsIsMissing","whenMapDispatchToPropsIsObject","default"]}},"../node_modules/react-redux/es/connect/mapStateToProps.js":{"id":"../node_modules/react-redux/es/connect/mapStateToProps.js","buildMeta":{"exportsType":"namespace","providedExports":["whenMapStateToPropsIsFunction","whenMapStateToPropsIsMissing","default"]}},"../node_modules/react-redux/es/connect/mergeProps.js":{"id":"../node_modules/react-redux/es/connect/mergeProps.js","buildMeta":{"exportsType":"namespace","providedExports":["defaultMergeProps","wrapMergePropsFunc","whenMergePropsIsFunction","whenMergePropsIsOmitted","default"]}},"../node_modules/react-redux/es/connect/selectorFactory.js":{"id":"../node_modules/react-redux/es/connect/selectorFactory.js","buildMeta":{"exportsType":"namespace","providedExports":["impureFinalPropsSelectorFactory","pureFinalPropsSelectorFactory","default"]}},"../node_modules/react-redux/es/connect/verifySubselectors.js":{"id":"../node_modules/react-redux/es/connect/verifySubselectors.js","buildMeta":{"exportsType":"namespace","providedExports":["default"]}},"../node_modules/react-redux/es/utils/warning.js":{"id":"../node_modules/react-redux/es/utils/warning.js","buildMeta":{"exportsType":"namespace","providedExports":["default"]}},"../node_modules/react-redux/es/utils/verifyPlainObject.js":{"id":"../node_modules/react-redux/es/utils/verifyPlainObject.js","buildMeta":{"exportsType":"namespace","providedExports":["default"]}},"../node_modules/react-redux/es/connect/wrapMapToProps.js":{"id":"../node_modules/react-redux/es/connect/wrapMapToProps.js","buildMeta":{"exportsType":"namespace","providedExports":["wrapMapToPropsConstant","getDependsOnOwnProps","wrapMapToPropsFunc"]}},"../node_modules/react-redux/es/utils/Subscription.js":{"id":"../node_modules/react-redux/es/utils/Subscription.js","buildMeta":{"exportsType":"namespace","providedExports":["default"]}},"../node_modules/react-redux/es/utils/PropTypes.js":{"id":"../node_modules/react-redux/es/utils/PropTypes.js","buildMeta":{"exportsType":"namespace","providedExports":["subscriptionShape","storeShape"]}},"../node_modules/redux/node_modules/symbol-observable/es/index.js":{"id":"../node_modules/redux/node_modules/symbol-observable/es/index.js","buildMeta":{"exportsType":"namespace","providedExports":["default"]}},"../node_modules/redux/node_modules/symbol-observable/es/ponyfill.js":{"id":"../node_modules/redux/node_modules/symbol-observable/es/ponyfill.js","buildMeta":{"exportsType":"namespace","providedExports":["default"]}},"../node_modules/react-router-dom/es/BrowserRouter.js":{"id":"../node_modules/react-router-dom/es/BrowserRouter.js","buildMeta":{"exportsType":"namespace","providedExports":["default"]}},"../node_modules/react-router-dom/es/HashRouter.js":{"id":"../node_modules/react-router-dom/es/HashRouter.js","buildMeta":{"exportsType":"namespace","providedExports":["default"]}},"../node_modules/react-router-dom/es/Link.js":{"id":"../node_modules/react-router-dom/es/Link.js","buildMeta":{"exportsType":"namespace","providedExports":["default"]}},"../node_modules/react-router-dom/es/MemoryRouter.js":{"id":"../node_modules/react-router-dom/es/MemoryRouter.js","buildMeta":{"exportsType":"namespace","providedExports":["default"]}},"../node_modules/react-router-dom/es/NavLink.js":{"id":"../node_modules/react-router-dom/es/NavLink.js","buildMeta":{"exportsType":"namespace","providedExports":["default"]}},"../node_modules/react-router-dom/es/Prompt.js":{"id":"../node_modules/react-router-dom/es/Prompt.js","buildMeta":{"exportsType":"namespace","providedExports":["default"]}},"../node_modules/react-router-dom/es/Redirect.js":{"id":"../node_modules/react-router-dom/es/Redirect.js","buildMeta":{"exportsType":"namespace","providedExports":["default"]}},"../node_modules/react-router-dom/es/Route.js":{"id":"../node_modules/react-router-dom/es/Route.js","buildMeta":{"exportsType":"namespace","providedExports":["default"]}},"../node_modules/react-router-dom/es/Router.js":{"id":"../node_modules/react-router-dom/es/Router.js","buildMeta":{"exportsType":"namespace","providedExports":["default"]}},"../node_modules/react-router-dom/es/StaticRouter.js":{"id":"../node_modules/react-router-dom/es/StaticRouter.js","buildMeta":{"exportsType":"namespace","providedExports":["default"]}},"../node_modules/react-router-dom/es/Switch.js":{"id":"../node_modules/react-router-dom/es/Switch.js","buildMeta":{"exportsType":"namespace","providedExports":["default"]}},"../node_modules/react-router-dom/es/matchPath.js":{"id":"../node_modules/react-router-dom/es/matchPath.js","buildMeta":{"exportsType":"namespace","providedExports":["default"]}},"../node_modules/react-router-dom/es/withRouter.js":{"id":"../node_modules/react-router-dom/es/withRouter.js","buildMeta":{"exportsType":"namespace","providedExports":["default"]}},"../node_modules/react-router/es/withRouter.js":{"id":"../node_modules/react-router/es/withRouter.js","buildMeta":{"exportsType":"namespace","providedExports":["default"]}},"../node_modules/react-router/es/Route.js":{"id":"../node_modules/react-router/es/Route.js","buildMeta":{"exportsType":"namespace","providedExports":["default"]}},"../node_modules/warning/browser.js":{"id":"../node_modules/warning/browser.js","buildMeta":{"providedExports":true}},"../node_modules/react-router/es/matchPath.js":{"id":"../node_modules/react-router/es/matchPath.js","buildMeta":{"exportsType":"namespace","providedExports":["default"]}},"../node_modules/react-router/node_modules/path-to-regexp/index.js":{"id":"../node_modules/react-router/node_modules/path-to-regexp/index.js","buildMeta":{"providedExports":true}},"../node_modules/react-router/node_modules/isarray/index.js":{"id":"../node_modules/react-router/node_modules/isarray/index.js","buildMeta":{"providedExports":true}},"../node_modules/react-router/es/Switch.js":{"id":"../node_modules/react-router/es/Switch.js","buildMeta":{"exportsType":"namespace","providedExports":["default"]}},"../node_modules/react-router/es/StaticRouter.js":{"id":"../node_modules/react-router/es/StaticRouter.js","buildMeta":{"exportsType":"namespace","providedExports":["default"]}},"../node_modules/history/PathUtils.js":{"id":"../node_modules/history/PathUtils.js","buildMeta":{"providedExports":true}},"../node_modules/react-router/es/Router.js":{"id":"../node_modules/react-router/es/Router.js","buildMeta":{"exportsType":"namespace","providedExports":["default"]}},"../node_modules/react-router/es/Redirect.js":{"id":"../node_modules/react-router/es/Redirect.js","buildMeta":{"exportsType":"namespace","providedExports":["default"]}},"../node_modules/history/es/index.js":{"id":"../node_modules/history/es/index.js","buildMeta":{"exportsType":"namespace","providedExports":["createBrowserHistory","createHashHistory","createMemoryHistory","createLocation","locationsAreEqual","parsePath","createPath"]}},"../node_modules/history/es/createBrowserHistory.js":{"id":"../node_modules/history/es/createBrowserHistory.js","buildMeta":{"exportsType":"namespace","providedExports":["default"]}},"../node_modules/history/es/createHashHistory.js":{"id":"../node_modules/history/es/createHashHistory.js","buildMeta":{"exportsType":"namespace","providedExports":["default"]}},"../node_modules/history/es/createMemoryHistory.js":{"id":"../node_modules/history/es/createMemoryHistory.js","buildMeta":{"exportsType":"namespace","providedExports":["default"]}},"../node_modules/history/es/LocationUtils.js":{"id":"../node_modules/history/es/LocationUtils.js","buildMeta":{"exportsType":"namespace","providedExports":["createLocation","locationsAreEqual"]}},"../node_modules/history/es/PathUtils.js":{"id":"../node_modules/history/es/PathUtils.js","buildMeta":{"exportsType":"namespace","providedExports":["addLeadingSlash","stripLeadingSlash","hasBasename","stripBasename","stripTrailingSlash","parsePath","createPath"]}},"../node_modules/resolve-pathname/index.js":{"id":"../node_modules/resolve-pathname/index.js","buildMeta":{"exportsType":"namespace","providedExports":["default"]}},"../node_modules/value-equal/index.js":{"id":"../node_modules/value-equal/index.js","buildMeta":{"exportsType":"namespace","providedExports":["default"]}},"../node_modules/history/es/createTransitionManager.js":{"id":"../node_modules/history/es/createTransitionManager.js","buildMeta":{"exportsType":"namespace","providedExports":["default"]}},"../node_modules/history/es/DOMUtils.js":{"id":"../node_modules/history/es/DOMUtils.js","buildMeta":{"exportsType":"namespace","providedExports":["canUseDOM","addEventListener","removeEventListener","getConfirmation","supportsHistory","supportsPopStateOnHashChange","supportsGoWithoutReloadUsingHash","isExtraneousPopstateEvent"]}},"../node_modules/react-router/es/Prompt.js":{"id":"../node_modules/react-router/es/Prompt.js","buildMeta":{"exportsType":"namespace","providedExports":["default"]}},"../node_modules/react-router/es/MemoryRouter.js":{"id":"../node_modules/react-router/es/MemoryRouter.js","buildMeta":{"exportsType":"namespace","providedExports":["default"]}},"../node_modules/history/createMemoryHistory.js":{"id":"../node_modules/history/createMemoryHistory.js","buildMeta":{"providedExports":true}},"../node_modules/history/LocationUtils.js":{"id":"../node_modules/history/LocationUtils.js","buildMeta":{"providedExports":true}},"../node_modules/history/createTransitionManager.js":{"id":"../node_modules/history/createTransitionManager.js","buildMeta":{"providedExports":true}},"../node_modules/history/createHashHistory.js":{"id":"../node_modules/history/createHashHistory.js","buildMeta":{"providedExports":true}},"../node_modules/history/DOMUtils.js":{"id":"../node_modules/history/DOMUtils.js","buildMeta":{"providedExports":true}},"../node_modules/history/createBrowserHistory.js":{"id":"../node_modules/history/createBrowserHistory.js","buildMeta":{"providedExports":true}},"../node_modules/react-dom/cjs/react-dom.development.js":{"id":"../node_modules/react-dom/cjs/react-dom.development.js","buildMeta":{"providedExports":true}},"../node_modules/fbjs/lib/ExecutionEnvironment.js":{"id":"../node_modules/fbjs/lib/ExecutionEnvironment.js","buildMeta":{"providedExports":true}},"../node_modules/fbjs/lib/getActiveElement.js":{"id":"../node_modules/fbjs/lib/getActiveElement.js","buildMeta":{"providedExports":true}},"../node_modules/fbjs/lib/shallowEqual.js":{"id":"../node_modules/fbjs/lib/shallowEqual.js","buildMeta":{"providedExports":true}},"../node_modules/fbjs/lib/containsNode.js":{"id":"../node_modules/fbjs/lib/containsNode.js","buildMeta":{"providedExports":true}},"../node_modules/fbjs/lib/emptyObject.js":{"id":"../node_modules/fbjs/lib/emptyObject.js","buildMeta":{"providedExports":true}},"../node_modules/fbjs/lib/hyphenateStyleName.js":{"id":"../node_modules/fbjs/lib/hyphenateStyleName.js","buildMeta":{"providedExports":true}},"../node_modules/fbjs/lib/camelizeStyleName.js":{"id":"../node_modules/fbjs/lib/camelizeStyleName.js","buildMeta":{"providedExports":true}},"../node_modules/fbjs/lib/camelize.js":{"id":"../node_modules/fbjs/lib/camelize.js","buildMeta":{"providedExports":true}},"../node_modules/fbjs/lib/hyphenate.js":{"id":"../node_modules/fbjs/lib/hyphenate.js","buildMeta":{"providedExports":true}},"../node_modules/fbjs/lib/isTextNode.js":{"id":"../node_modules/fbjs/lib/isTextNode.js","buildMeta":{"providedExports":true}},"../node_modules/fbjs/lib/isNode.js":{"id":"../node_modules/fbjs/lib/isNode.js","buildMeta":{"providedExports":true}},"../node_modules/react/cjs/react.development.js":{"id":"../node_modules/react/cjs/react.development.js","buildMeta":{"providedExports":true}}}}